<?xml version="1.0" encoding="ISO-8859-1"?> 
<?xml-stylesheet href="latest_ob.xsl" type="text/xsl"?>
<current_observation version="1.0"
	 xmlns:xsd="http://www.w3.org/2001/XMLSchema"
	 xmlns:xsi="http://www.w3.org/2001/XMLSchema-instance"
	 xsi:noNamespaceSchemaLocation="http://www.weather.gov/view/current_observation.xsd">
	<credit>NOAA's National Weather Service</credit>
	<credit_URL>http://weather.gov/</credit_URL>
	<image>
		<url>http://weather.gov/images/xml_logo.gif</url>
		<title>NOAA's National Weather Service</title>
		<link>http://weather.gov</link>
	</image>
	<suggested_pickup>15 minutes after the hour</suggested_pickup>
	<suggested_pickup_period>60</suggested_pickup_period>
	<location>MBM2</location>
	<station_id>46093</station_id>
	<latitude>36.69</latitude>
	<longitude>-122.41</longitude>
	<observation_time>Last Updated on Sep 29 2011, 8:16 am PDT</observation_time>
        <observation_time_rfc822>Thu, 29 Sep 2011 08:16:00 -0700</observation_time_rfc822>
	<temperature_string>57.6 F (14.2 C)</temperature_string>
	<temp_f>57.6</temp_f>
	<temp_c>14.2</temp_c>
	<water_temp_f>57.9</water_temp_f>
	<water_temp_c>14.4</water_temp_c>
	<wind_string>Southeast at 13.4 MPH (11.66 KT)</wind_string>
	<wind_dir>Southeast</wind_dir>
	<wind_degrees>130</wind_degrees>
	<wind_mph>13.4</wind_mph>
	<wind_gust_mph>0.0</wind_gust_mph>
	<wind_kt>11.66</wind_kt>
	<pressure_string>1014.1 mb</pressure_string>
	<pressure_mb>1014.1</pressure_mb>
	<pressure_tendency_mb>0.7</pressure_tendency_mb>
	<windchill_string>55 F (13 C)</windchill_string>
      	<windchill_f>55</windchill_f>
      	<windchill_c>13</windchill_c>
	<mean_wave_dir>Northwest</mean_wave_dir>
	<mean_wave_degrees></mean_wave_degrees>
	<disclaimer_url>http://weather.gov/disclaimer.html</disclaimer_url>
	<copyright_url>http://weather.gov/disclaimer.html</copyright_url>
	<privacy_policy_url>http://weather.gov/notice.html</privacy_policy_url>
</current_observation>
